LICENSE.md
README.md
disptrans.py
setup.py
disptrans.egg-info/PKG-INFO
disptrans.egg-info/SOURCES.txt
disptrans.egg-info/dependency_links.txt
disptrans.egg-info/requires.txt
disptrans.egg-info/top_level.txt