Metadata-Version: 2.1
Name: disptrans
Version: 0.0.1
Summary: Dispersion-compensated algorithm for electromagnetic waveguides
Home-page: https://github.com/garrettj403/DispersionTransform/
Author: John Garrett
Author-email: garrettj403@gmail.com
License: MIT
Project-URL: Changelog, https://github.com/garrettj403/DispersionTransform/blob/master/CHANGES.md
Project-URL: Issue Tracker, https://github.com/garrettj403/DispersionTransform/issues
Keywords: dispersion,waveguide,signal-processing,dsp
Platform: any
Classifier: Intended Audience :: Science/Research
Classifier: License :: OSI Approved :: MIT License
Classifier: Natural Language :: English
Classifier: Programming Language :: Python :: 3.5
Classifier: Programming Language :: Python :: 3.6
Classifier: Programming Language :: Python :: 3.7
Provides-Extra: testing
Provides-Extra: examples
License-File: LICENSE.md
